mojtaba_message/__init__.py
mojtaba_message/message.py
mojtaba_message-0.1.0.dist-info/licenses/LICENSE
mojtaba_message-0.1.0.dist-info/METADATA
mojtaba_message-0.1.0.dist-info/WHEEL
mojtaba_message-0.1.0.dist-info/top_level.txt
mojtaba_message-0.1.0.dist-info/RECORD
