Metadata-Version: 2.4
Name: mojtaba-message
Version: 0.1.0
Summary: A simple message package by Mojtaba
Home-page: https://github.com/yourusername/mojtaba-message
Author: Your Name
Author-email: your@email.com
Classifier: Programming Language :: Python :: 3
Classifier: License :: OSI Approved :: MIT License
Requires-Python: >=3.6
License-File: LICENSE
Dynamic: author
Dynamic: author-email
Dynamic: classifier
Dynamic: description
Dynamic: description-content-type
Dynamic: home-page
Dynamic: license-file
Dynamic: requires-python
Dynamic: summary
